autodiffpypi/__init__.py
autodiffpypi/base_derivatives.py
autodiffpypi/dual_number.py
autodiffpypi/forward_mode.py
autodiffpypi/mixed_mode.py
autodiffpypi/reverse_mode.py
autodiffpypi-1.0.0.dist-info/METADATA
autodiffpypi-1.0.0.dist-info/WHEEL
autodiffpypi-1.0.0.dist-info/licenses/LICENSE
autodiffpypi-1.0.0.dist-info/RECORD
