Metadata-Version: 2.1
Name: autodiffpypi
Version: 1.0.0
Summary: An Automatic Differentiation Package
Project-URL: Github repo, https://code.harvard.edu/CS107
Author-email: Ido Burstein <idoburstein@college.harvard.edu>, Sylvia Cruz-Albrecht <sylvia_cruzalbrecht@college.harvard.edu>, Ty Geri <tygeri@college.harvard.edu>, Dante Lacuadra <dlacuadra@college.harvard.edu>, Natalie Melas-Kyriazi <nmelaskyriazi@college.harvard.edu>
License-File: LICENSE
Classifier: License :: OSI Approved :: MIT License
Classifier: Operating System :: OS Independent
Classifier: Programming Language :: Python :: 3
Requires-Python: >=3.7
